{
	"name": "Test Terminal",
	"locked": true,
	"password": "fo",
	"attempts": 3,
	"content": "Welcome to ROBCO Industries (TM) Termlink\nClearance: Test Terminal",
	"screens": [{
		"name": "SCREEN 1 TITLE",
		"content": "This is screen 1 content",
		"screens": [{
			"name": "SCREEN 1.1 SUBTITLE",
			"content": "This is screen 1.1 content, subsection of screen 1"
		}]
	}, {
		"name": "SCREN 2 TITLE",
		"content": "This is screen 2 content"
	}, {
		"name": "SCREEN 3 TITLE",
		"content": "This is screen 3 content"
	}]
}